phonexia_replay_attack_detection_client.py
phonexia_replay_attack_detection_client-2.1.0.dist-info/METADATA
phonexia_replay_attack_detection_client-2.1.0.dist-info/WHEEL
phonexia_replay_attack_detection_client-2.1.0.dist-info/entry_points.txt
phonexia_replay_attack_detection_client-2.1.0.dist-info/top_level.txt
phonexia_replay_attack_detection_client-2.1.0.dist-info/RECORD
